colourpycker/__init__.py
colourpycker/colourpycker.py
colourpycker-0.0.6.dist-info/METADATA
colourpycker-0.0.6.dist-info/WHEEL
colourpycker-0.0.6.dist-info/LICENSE
colourpycker-0.0.6.dist-info/RECORD
