Metadata-Version: 2.1
Name: colourpycker
Version: 0.0.6
Summary: A Python package that can be used to extract colours from images for use in data visualization projects.
Home-page: https://github.com/UBC-MDS/colourpycker
License: MIT
Author: Shaun Hutchinson, Arjun Radhakrishnan, Alex Taciuk and Lauren Zung
Requires-Python: >=3.9,<4.0
Classifier: License :: OSI Approved :: MIT License
Classifier: Programming Language :: Python :: 3
Classifier: Programming Language :: Python :: 3.9
Classifier: Programming Language :: Python :: 3.10
Classifier: Programming Language :: Python :: 3.11
Requires-Dist: altair (>=4.2.0,<5.0.0)
Requires-Dist: extcolors (>=1.0.0,<2.0.0)
Requires-Dist: matplotlib (>=3.6.3,<4.0.0)
Requires-Dist: numpy (>=1.24.1,<2.0.0)
Requires-Dist: pandas (>=1.5.2,<2.0.0)
Requires-Dist: pillow (>=9.4.0,<10.0.0)
Requires-Dist: python-semantic-release (>=7.33.0,<8.0.0)
Requires-Dist: requests (>=2.28.2,<3.0.0)
Project-URL: Documentation, https://colourpycker.readthedocs.io
Project-URL: Repository, https://github.com/UBC-MDS/colourpycker
